LICENSE
README.md
setup.py
Calculator_tvain.egg-info/PKG-INFO
Calculator_tvain.egg-info/SOURCES.txt
Calculator_tvain.egg-info/dependency_links.txt
Calculator_tvain.egg-info/top_level.txt
src/Calculator.py
src/__init__.py