Metadata-Version: 2.1
Name: Calculator_tvain
Version: 0.0.2
Summary: Performs basic arithmetic operations
Home-page: https://github.com/TuringCollegeSubmissions/tvaino-DWWP.1.5/tree/master/Calculator_pack
Author: Tomas Vainoras
Author-email: vainoras@gmail.com
Classifier: Programming Language :: Python :: 3
License-File: LICENSE
